LICENSE.txt
MANIFEST.in
README.rst
setup.cfg
setup.py
ak_isign.egg-info/PKG-INFO
ak_isign.egg-info/SOURCES.txt
ak_isign.egg-info/dependency_links.txt
ak_isign.egg-info/requires.txt
ak_isign.egg-info/top_level.txt
bin/isign
bin/isign_export_creds.sh
bin/isign_guess_mobileprovision.sh
bin/multisign
isign/__init__.py
isign/archive.py
isign/bundle.py
isign/code_resources.py
isign/code_resources_template.xml
isign/codesig.py
isign/exceptions.py
isign/isign.py
isign/macho.py
isign/macho_cs.py
isign/makesig.py
isign/multisign.py
isign/signable.py
isign/signer.py
isign/utils.py
isign/apple_credentials/applecerts.pem
tests/test_archive.py
tests/test_creds_dir.py
tests/test_entitlements.py
tests/test_helpers.py
tests/test_multisign.py
tests/test_parsing.py
tests/test_public_interface.py
tests/test_sig.py
tests/test_versioning.py
tests/test_versus_apple.py