Metadata-Version: 2.1
Name: ak-isign
Version: 0.10.18
Summary: Re-signing iOS apps without Apple tools
Home-page: https://github.com/saucelabs/ak_isign
Download-URL: https://github.com/saucelabs/ak_isign/tarball/v0.10.18
Author: Sauce Labs
Author-email: dev@saucelabs.com
Keywords: ios,app,signature,codesign,sign,resign
Classifier: Development Status :: 5 - Production/Stable
Classifier: Intended Audience :: Developers
Classifier: Topic :: Utilities
Classifier: License :: OSI Approved :: Apache Software License
Classifier: Programming Language :: Python :: 2.7
License-File: LICENSE.txt
